Workbook
Name clusters: Кластеры!$A$1:$A$167
Name correlations: Корреляции!$A$1:$A$5
Name data_clean: Данные!$A$1:$F$3358
Name forecast: Прогноз!$A$1:$A$16
Name hypotheses: Гипотезы!$A$1:$A$8

Sheet Данные
A1: ID клиента | B1: Товар | C1: Сумма | D1: Дата | E1: Рейтинг | F1: Способ оплаты | G1: Месяц
A2: 3992 | B2: Backpack | C2: 101 | D2: 44908 | E2: 1.3 | F2: Credit Card | G2: =TEXT(D2,"ГГГГ-ММ") -> 2022-12
A3: 4105 | B3: Dress | C3: 164 | D3: 44854 | E3: 1.2 | F3: Credit Card | G3: =TEXT(D3,"ГГГГ-ММ") -> 2022-10
A4: 4119 | B4: Boots | C4: 21 | D4: 45019 | E4: 3.9 | F4: Cash | G4: =TEXT(D4,"ГГГГ-ММ") -> 2023-04
A5: 3957 | B5: Camisole | C5: 147 | D5: 44869 | E5: 4.7 | F5: Cash | G5: =TEXT(D5,"ГГГГ-ММ") -> 2022-11
A6: 3994 | B6: Loafers | C6: 114.77966 | D6: 45062 | E6: 3.9 | F6: Cash | G6: =TEXT(D6,"ГГГГ-ММ") -> 2023-05
A7: 3995 | B7: Bowtie | C7: 30 | D7: 44888 | E7: 4.1 | F7: Cash | G7: =TEXT(D7,"ГГГГ-ММ") -> 2022-11
A8: 4072 | B8: Poncho | C8: 170 | D8: 44849 | E8: 3.6 | F8: Credit Card | G8: =TEXT(D8,"ГГГГ-ММ") -> 2022-10
A9: 4093 | B9: Trousers | C9: 102 | D9: 45071 | E9: 2.1 | F9: Cash | G9: =TEXT(D9,"ГГГГ-ММ") -> 2023-05
A10: 4031 | B10: Blouse | C10: 190 | D10: 44940 | E10: 3 | F10: Cash | G10: =TEXT(D10,"ГГГГ-ММ") -> 2023-01
A11: 4056 | B11: Sneakers | C11: 109.08475 | D11: 44867 | E11: 3.0693548 | F11: Credit Card | G11: =TEXT(D11,"ГГГГ-ММ") -> 2022-11
A12: 4114 | B12: Leggings | C12: 84 | D12: 45092 | E12: 3.8 | F12: Cash | G12: =TEXT(D12,"ГГГГ-ММ") -> 2023-06
A13: 4104 | B13: Backpack | C13: 69 | D13: 45073 | E13: 2.1 | F13: Cash | G13: =TEXT(D13,"ГГГГ-ММ") -> 2023-05
... A3358: 4001 | B3358: Backpack | C3358: 115 | D3358: 45007 | E3358: 1.4 | F3358: Cash | G3358: =TEXT(D3358,"ГГГГ-ММ") -> 2023-03

Sheet Сводка
A1: Метрика | B1: Значение
A2: Всего строк | B2: =COUNTA(Данные!A:A)-1 -> 3357
A3: Уникальных клиентов | B3: =SUMPRODUCT(1/COUNTIF(Данные!A2:A3358, Данные!A2:A3358)) -> 166
A4: Уникальных товаров | B4: =SUMPRODUCT(1/COUNTIF(Данные!B2:B3358, Данные!B2:B3358)) -> 50
A5: Общая выручка | B5: =SUM(Данные!C:C) -> 357025.63
A6: Средний чек | B6: =AVERAGE(Данные!C:C) -> 106.35258
A7: Медиана чека | B7: =MEDIAN(Данные!C:C) -> 107
A8: Ст. отклонение | B8: =_xlfn.STDEV.S(Данные!C:C) -> 49.770592
A9: Минимальный чек | B9: =MIN(Данные!C:C) -> 10
A10: Максимальный чек | B10: =MAX(Данные!C:C) -> 200
A11: Q1 (25%) | B11: =_xlfn.QUARTILE.INC(Данные!C:C, 1) -> 70
A12: Q3 (75%) | B12: =_xlfn.QUARTILE.INC(Данные!C:C, 3) -> 144
A13: IQR | B13: =B12-B11 -> 74
A14: Средний рейтинг | B14: =AVERAGE(Данные!E:E) -> 2.995061
A15: Медиана рейтинга | B15: =MEDIAN(Данные!E:E) -> 3
A16: Первая покупка | B16: =MIN(Данные!D:D) -> 44836
A17: Последняя покупка | B17: =MAX(Данные!D:D) -> 45200

Sheet Товары
A1: Названия строк | B1: Средний чек | C1: Выручка | D1: Средний рейтинг | E1: Кол-во покупок
A2: янв | B2: 105.07887 | C2: 30472.873 | D2: 2.9806059 | E2: 290
A3: фев | B3: 104.63132 | C3: 25843.935 | D3: 2.9999084 | E3: 247
A4: мар | B4: 113.01945 | C4: 30741.29 | D4: 2.9699543 | E4: 272
A5: апр | B5: 105.97453 | C5: 30732.615 | D5: 3.104516 | E5: 290
A6: май | B6: 104.68585 | C6: 31615.126 | D6: 3.0370073 | E6: 302
A7: июн | B7: 115.7247 | C7: 29972.696 | D7: 2.9636058 | E7: 259
A8: июл | B8: 104.44149 | C8: 31332.448 | D8: 3.0464339 | E8: 300
A9: авг | B9: 105.73085 | C9: 31507.794 | D9: 3.0333347 | E9: 298
A10: сен | B10: 105.33111 | C10: 26543.439 | D10: 2.8447659 | E10: 252
A11: окт | B11: 99.481022 | C11: 31038.079 | D11: 3.113817 | E11: 312
A12: ноя | B12: 107.07086 | C12: 25054.581 | D12: 2.9567883 | E12: 234
A13: дек | B13: 106.87958 | C13: 32170.752 | D13: 2.85726 | E13: 301
A14: Общий итог | B14: 106.35258 | C14: 357025.63 | D14: 2.9956568 | E14: 3357

Sheet ABC-анализ
A1: Названия строк | B1: Средний чек | C1: Средний рейтинг | D1: Кол-во покупок | E1: Выручка | F1: Доля % | G1: Накопленная доля % | H1: АВС-класс
A2: Skirt | B2: 105.1 | C2: 3.1962963 | D2: 88 | E2: =SUMIF(Данные!B:B,A2,Данные!C:C) -> 9248.8 | F2: =E2/SUM($E$2:$E$51) -> 0.025905143 | G2: =F2 -> 0.025905143 | H2: =IF(G2<=0.5,"A",IF(G2<=0.8,"B","C")) -> A
A3: Shorts | B3: 107.26027 | C3: 2.9 | D3: 86 | E3: =SUMIF(Данные!B:B,A3,Данные!C:C) -> 9224.3836 | F3: =E3/SUM($E$2:$E$51) -> 0.025836755 | G3: =G2+F3 -> 0.051741898 | H3: =IF(G3<=0.5,"A",IF(G3<=0.8,"B","C")) -> A
A4: T-shirt | B4: 111.85484 | C4: 3 | D4: 81 | E4: =SUMIF(Данные!B:B,A4,Данные!C:C) -> 9060.2419 | F4: =E4/SUM($E$2:$E$51) -> 0.025377007 | G4: =G3+F4 -> 0.077118905 | H4: =IF(G4<=0.5,"A",IF(G4<=0.8,"B","C")) -> A
A5: Pajamas | B5: 112.74576 | C5: 2.8291667 | D5: 79 | E5: =SUMIF(Данные!B:B,A5,Данные!C:C) -> 8906.9153 | F5: =E5/SUM($E$2:$E$51) -> 0.024947552 | G5: =G4+F5 -> 0.10206646 | H5: =IF(G5<=0.5,"A",IF(G5<=0.8,"B","C")) -> A
A6: Belt | B6: 97.720588 | C6: 3.0156627 | D6: 89 | E6: =SUMIF(Данные!B:B,A6,Данные!C:C) -> 8697.1324 | F6: =E6/SUM($E$2:$E$51) -> 0.024359967 | G6: =G5+F6 -> 0.12642642 | H6: =IF(G6<=0.5,"A",IF(G6<=0.8,"B","C")) -> A
A7: Blouse | B7: 120.375 | C7: 2.9190476 | D7: 72 | E7: =SUMIF(Данные!B:B,A7,Данные!C:C) -> 8667 | F7: =E7/SUM($E$2:$E$51) -> 0.024275568 | G7: =G6+F7 -> 0.15070199 | H7: =IF(G7<=0.5,"A",IF(G7<=0.8,"B","C")) -> A
A8: Loafers | B8: 114.77966 | C8: 2.8333333 | D8: 75 | E8: =SUMIF(Данные!B:B,A8,Данные!C:C) -> 8608.4746 | F8: =E8/SUM($E$2:$E$51) -> 0.024111643 | G8: =G7+F8 -> 0.17481364 | H8: =IF(G8<=0.5,"A",IF(G8<=0.8,"B","C")) -> A
A9: Raincoat | B9: 123.21818 | C9: 3 | D9: 69 | E9: =SUMIF(Данные!B:B,A9,Данные!C:C) -> 8502.0545 | F9: =E9/SUM($E$2:$E$51) -> 0.023813569 | G9: =G8+F9 -> 0.1986272 | H9: =IF(G9<=0.5,"A",IF(G9<=0.8,"B","C")) -> A
A10: Hoodie | B10: 113.54098 | C10: 2.9647059 | D10: 74 | E10: =SUMIF(Данные!B:B,A10,Данные!C:C) -> 8402.0328 | F10: =E10/SUM($E$2:$E$51) -> 0.023533417 | G10: =G9+F10 -> 0.22216062 | H10: =IF(G10<=0.5,"A",IF(G10<=0.8,"B","C")) -> A
A11: Onesie | B11: 114.39655 | C11: 2.9761905 | D11: 70 | E11: =SUMIF(Данные!B:B,A11,Данные!C:C) -> 8007.7586 | F11: =E11/SUM($E$2:$E$51) -> 0.022429086 | G11: =G10+F11 -> 0.24458971 | H11: =IF(G11<=0.5,"A",IF(G11<=0.8,"B","C")) -> A
A12: Backpack | B12: 112.14545 | C12: 3.0636364 | D12: 71 | E12: =SUMIF(Данные!B:B,A12,Данные!C:C) -> 7962.3273 | F12: =E12/SUM($E$2:$E$51) -> 0.022301837 | G12: =G11+F12 -> 0.26689154 | H12: =IF(G12<=0.5,"A",IF(G12<=0.8,"B","C")) -> A
A13: Cardigan | B13: 110.56667 | C13: 3.058209 | D13: 71 | E13: =SUMIF(Данные!B:B,A13,Данные!C:C) -> 7850.2333 | F13: =E13/SUM($E$2:$E$51) -> 0.021987871 | G13: =G12+F13 -> 0.28887941 | H13: =IF(G13<=0.5,"A",IF(G13<=0.8,"B","C")) -> A
A14: Wallet | B14: 107.94915 | C14: 3.1651515 | D14: 72 | E14: =SUMIF(Данные!B:B,A14,Данные!C:C) -> 7772.339 | F14: =E14/SUM($E$2:$E$51) -> 0.021769695 | G14: =G13+F14 -> 0.31064911 | H14: =IF(G14<=0.5,"A",IF(G14<=0.8,"B","C")) -> A
... A51: Sun Hat | B51: 97.071429 | C51: 3.4933333 | D51: 50 | E51: =SUMIF(Данные!B:B,A51,Данные!C:C) -> 4853.5714 | F51: =E51/SUM($E$2:$E$51) -> 0.013594462 | G51: =G50+F51 -> 1 | H51: =IF(G51<=0.5,"A",IF(G51<=0.8,"B","C")) -> C

Sheet Оплата
A1: Способ оплаты | B1: Кол-во | C1: Выручка | D1: Средний чек | E1: Средний рейтинг | F1: Доля, %
A2: Кредитная карта | B2: =COUNTIF(Данные!F:F,"Credit Card") -> 1746 | C2: =SUMIF(Данные!F:F,"Credit Card",Данные!C:C) -> 184462.16 | D2: =AVERAGEIF(Данные!F:F,"Credit Card",Данные!C:C) -> 105.64843 | E2: =AVERAGEIF(Данные!F:F,"Credit Card",Данные!E:E) -> 2.999483 | F2: =B2/$B$4*100 -> 52.010724
A3: Наличные | B3: =COUNTIF(Данные!F:F,"Cash") -> 1611 | C3: =SUMIF(Данные!F:F,"Cash",Данные!C:C) -> 172563.47 | D3: =AVERAGEIF(Данные!F:F,"Cash",Данные!C:C) -> 107.11575 | E3: =AVERAGEIF(Данные!F:F,"Cash",Данные!E:E) -> 2.9902686 | F3: =B3/$B$4*100 -> 47.989276
A4: Итого: | B4: =SUM(B2:B3) -> 3357 | C4: =SUM(C2:C3) -> 357025.63 | D4: =C4/B4 -> 106.35258 | E4: =AVERAGE(Данные!E:E) -> 2.995061 | F4: =SUM(F2:F3) -> 100

Sheet RFM
A1: ID клиента | B1: Последняя покупка | C1: Частота | D1: Сумма покупок | E1: R_Дней | F1: R_score | G1: F_score | H1: M_score | I1: RFM_score | J1: Сегмент
A2: 3957 | B2: 45115 | C2: 14 | D2: 1473.9702 | E2: =DATE(2023,10,1)-B2 -> 85 | F2: =IF(E2<=30,5,IF(E2<=60,4,IF(E2<=90,3,IF(E2<=180,2,1)))) -> 3 | G2: =IF(C2>=25,5,IF(C2>=20,4,IF(C2>=15,3,IF(C2>=10,2,1)))) -> 2 | H2: =IF(D2>=2500,5,IF(D2>=2000,4,IF(D2>=1500,3,IF(D2>=1000,2,1)))) -> 2 | I2: =F2+G2+H2 -> 7 | J2: =IF(AND(F2>=4,G2>=4,H2>=4),"Чемпионы",IF(AND(F2>=3,G2>=4),"Лояльные",IF(AND(F2>=4,G2<=2),"Новые",IF(AND(F2<=2,G2>=4),"В зоне риска",IF(AND(F2<=2,G2<=2),"Потерянные","Прочие"))))) -> Прочие
A3: 3958 | B3: 45183 | C3: 20 | D3: 1673.528 | E3: =DATE(2023,10,1)-B3 -> 17 | F3: =IF(E3<=30,5,IF(E3<=60,4,IF(E3<=90,3,IF(E3<=180,2,1)))) -> 5 | G3: =IF(C3>=25,5,IF(C3>=20,4,IF(C3>=15,3,IF(C3>=10,2,1)))) -> 4 | H3: =IF(D3>=2500,5,IF(D3>=2000,4,IF(D3>=1500,3,IF(D3>=1000,2,1)))) -> 3 | I3: =F3+G3+H3 -> 12 | J3: =IF(AND(F3>=4,G3>=4,H3>=4),"Чемпионы",IF(AND(F3>=3,G3>=4),"Лояльные",IF(AND(F3>=4,G3<=2),"Новые",IF(AND(F3<=2,G3>=4),"В зоне риска",IF(AND(F3<=2,G3<=2),"Потерянные","Прочие"))))) -> Лояльные
A4: 3959 | B4: 45172 | C4: 22 | D4: 2347.5411 | E4: =DATE(2023,10,1)-B4 -> 28 | F4: =IF(E4<=30,5,IF(E4<=60,4,IF(E4<=90,3,IF(E4<=180,2,1)))) -> 5 | G4: =IF(C4>=25,5,IF(C4>=20,4,IF(C4>=15,3,IF(C4>=10,2,1)))) -> 4 | H4: =IF(D4>=2500,5,IF(D4>=2000,4,IF(D4>=1500,3,IF(D4>=1000,2,1)))) -> 4 | I4: =F4+G4+H4 -> 13 | J4: =IF(AND(F4>=4,G4>=4,H4>=4),"Чемпионы",IF(AND(F4>=3,G4>=4),"Лояльные",IF(AND(F4>=4,G4<=2),"Новые",IF(AND(F4<=2,G4>=4),"В зоне риска",IF(AND(F4<=2,G4<=2),"Потерянные","Прочие"))))) -> Чемпионы
A5: 3960 | B5: 45183 | C5: 18 | D5: 1723.7942 | E5: =DATE(2023,10,1)-B5 -> 17 | F5: =IF(E5<=30,5,IF(E5<=60,4,IF(E5<=90,3,IF(E5<=180,2,1)))) -> 5 | G5: =IF(C5>=25,5,IF(C5>=20,4,IF(C5>=15,3,IF(C5>=10,2,1)))) -> 3 | H5: =IF(D5>=2500,5,IF(D5>=2000,4,IF(D5>=1500,3,IF(D5>=1000,2,1)))) -> 3 | I5: =F5+G5+H5 -> 11 | J5: =IF(AND(F5>=4,G5>=4,H5>=4),"Чемпионы",IF(AND(F5>=3,G5>=4),"Лояльные",IF(AND(F5>=4,G5<=2),"Новые",IF(AND(F5<=2,G5>=4),"В зоне риска",IF(AND(F5<=2,G5<=2),"Потерянные","Прочие"))))) -> Прочие
A6: 3961 | B6: 45167 | C6: 22 | D6: 2328.6671 | E6: =DATE(2023,10,1)-B6 -> 33 | F6: =IF(E6<=30,5,IF(E6<=60,4,IF(E6<=90,3,IF(E6<=180,2,1)))) -> 4 | G6: =IF(C6>=25,5,IF(C6>=20,4,IF(C6>=15,3,IF(C6>=10,2,1)))) -> 4 | H6: =IF(D6>=2500,5,IF(D6>=2000,4,IF(D6>=1500,3,IF(D6>=1000,2,1)))) -> 4 | I6: =F6+G6+H6 -> 12 | J6: =IF(AND(F6>=4,G6>=4,H6>=4),"Чемпионы",IF(AND(F6>=3,G6>=4),"Лояльные",IF(AND(F6>=4,G6<=2),"Новые",IF(AND(F6<=2,G6>=4),"В зоне риска",IF(AND(F6<=2,G6<=2),"Потерянные","Прочие"))))) -> Чемпионы
A7: 3962 | B7: 45194 | C7: 22 | D7: 2559.3489 | E7: =DATE(2023,10,1)-B7 -> 6 | F7: =IF(E7<=30,5,IF(E7<=60,4,IF(E7<=90,3,IF(E7<=180,2,1)))) -> 5 | G7: =IF(C7>=25,5,IF(C7>=20,4,IF(C7>=15,3,IF(C7>=10,2,1)))) -> 4 | H7: =IF(D7>=2500,5,IF(D7>=2000,4,IF(D7>=1500,3,IF(D7>=1000,2,1)))) -> 5 | I7: =F7+G7+H7 -> 14 | J7: =IF(AND(F7>=4,G7>=4,H7>=4),"Чемпионы",IF(AND(F7>=3,G7>=4),"Лояльные",IF(AND(F7>=4,G7<=2),"Новые",IF(AND(F7<=2,G7>=4),"В зоне риска",IF(AND(F7<=2,G7<=2),"Потерянные","Прочие"))))) -> Чемпионы
A8: 3963 | B8: 45196 | C8: 20 | D8: 2203.9572 | E8: =DATE(2023,10,1)-B8 -> 4 | F8: =IF(E8<=30,5,IF(E8<=60,4,IF(E8<=90,3,IF(E8<=180,2,1)))) -> 5 | G8: =IF(C8>=25,5,IF(C8>=20,4,IF(C8>=15,3,IF(C8>=10,2,1)))) -> 4 | H8: =IF(D8>=2500,5,IF(D8>=2000,4,IF(D8>=1500,3,IF(D8>=1000,2,1)))) -> 4 | I8: =F8+G8+H8 -> 13 | J8: =IF(AND(F8>=4,G8>=4,H8>=4),"Чемпионы",IF(AND(F8>=3,G8>=4),"Лояльные",IF(AND(F8>=4,G8<=2),"Новые",IF(AND(F8<=2,G8>=4),"В зоне риска",IF(AND(F8<=2,G8<=2),"Потерянные","Прочие"))))) -> Чемпионы
A9: 3964 | B9: 45193 | C9: 22 | D9: 2335.7864 | E9: =DATE(2023,10,1)-B9 -> 7 | F9: =IF(E9<=30,5,IF(E9<=60,4,IF(E9<=90,3,IF(E9<=180,2,1)))) -> 5 | G9: =IF(C9>=25,5,IF(C9>=20,4,IF(C9>=15,3,IF(C9>=10,2,1)))) -> 4 | H9: =IF(D9>=2500,5,IF(D9>=2000,4,IF(D9>=1500,3,IF(D9>=1000,2,1)))) -> 4 | I9: =F9+G9+H9 -> 13 | J9: =IF(AND(F9>=4,G9>=4,H9>=4),"Чемпионы",IF(AND(F9>=3,G9>=4),"Лояльные",IF(AND(F9>=4,G9<=2),"Новые",IF(AND(F9<=2,G9>=4),"В зоне риска",IF(AND(F9<=2,G9<=2),"Потерянные","Прочие"))))) -> Чемпионы
A10: 3965 | B10: 45197 | C10: 19 | D10: 2025.6852 | E10: =DATE(2023,10,1)-B10 -> 3 | F10: =IF(E10<=30,5,IF(E10<=60,4,IF(E10<=90,3,IF(E10<=180,2,1)))) -> 5 | G10: =IF(C10>=25,5,IF(C10>=20,4,IF(C10>=15,3,IF(C10>=10,2,1)))) -> 3 | H10: =IF(D10>=2500,5,IF(D10>=2000,4,IF(D10>=1500,3,IF(D10>=1000,2,1)))) -> 4 | I10: =F10+G10+H10 -> 12 | J10: =IF(AND(F10>=4,G10>=4,H10>=4),"Чемпионы",IF(AND(F10>=3,G10>=4),"Лояльные",IF(AND(F10>=4,G10<=2),"Новые",IF(AND(F10<=2,G10>=4),"В зоне риска",IF(AND(F10<=2,G10<=2),"Потерянные","Прочие"))))) -> Прочие
A11: 3966 | B11: 45186 | C11: 18 | D11: 2166.1265 | E11: =DATE(2023,10,1)-B11 -> 14 | F11: =IF(E11<=30,5,IF(E11<=60,4,IF(E11<=90,3,IF(E11<=180,2,1)))) -> 5 | G11: =IF(C11>=25,5,IF(C11>=20,4,IF(C11>=15,3,IF(C11>=10,2,1)))) -> 3 | H11: =IF(D11>=2500,5,IF(D11>=2000,4,IF(D11>=1500,3,IF(D11>=1000,2,1)))) -> 4 | I11: =F11+G11+H11 -> 12 | J11: =IF(AND(F11>=4,G11>=4,H11>=4),"Чемпионы",IF(AND(F11>=3,G11>=4),"Лояльные",IF(AND(F11>=4,G11<=2),"Новые",IF(AND(F11<=2,G11>=4),"В зоне риска",IF(AND(F11<=2,G11<=2),"Потерянные","Прочие"))))) -> Прочие
A12: 3967 | B12: 45195 | C12: 21 | D12: 2186.8644 | E12: =DATE(2023,10,1)-B12 -> 5 | F12: =IF(E12<=30,5,IF(E12<=60,4,IF(E12<=90,3,IF(E12<=180,2,1)))) -> 5 | G12: =IF(C12>=25,5,IF(C12>=20,4,IF(C12>=15,3,IF(C12>=10,2,1)))) -> 4 | H12: =IF(D12>=2500,5,IF(D12>=2000,4,IF(D12>=1500,3,IF(D12>=1000,2,1)))) -> 4 | I12: =F12+G12+H12 -> 13 | J12: =IF(AND(F12>=4,G12>=4,H12>=4),"Чемпионы",IF(AND(F12>=3,G12>=4),"Лояльные",IF(AND(F12>=4,G12<=2),"Новые",IF(AND(F12<=2,G12>=4),"В зоне риска",IF(AND(F12<=2,G12<=2),"Потерянные","Прочие"))))) -> Чемпионы
A13: 3968 | B13: 45190 | C13: 25 | D13: 2529.1524 | E13: =DATE(2023,10,1)-B13 -> 10 | F13: =IF(E13<=30,5,IF(E13<=60,4,IF(E13<=90,3,IF(E13<=180,2,1)))) -> 5 | G13: =IF(C13>=25,5,IF(C13>=20,4,IF(C13>=15,3,IF(C13>=10,2,1)))) -> 5 | H13: =IF(D13>=2500,5,IF(D13>=2000,4,IF(D13>=1500,3,IF(D13>=1000,2,1)))) -> 5 | I13: =F13+G13+H13 -> 15 | J13: =IF(AND(F13>=4,G13>=4,H13>=4),"Чемпионы",IF(AND(F13>=3,G13>=4),"Лояльные",IF(AND(F13>=4,G13<=2),"Новые",IF(AND(F13<=2,G13>=4),"В зоне риска",IF(AND(F13<=2,G13<=2),"Потерянные","Прочие"))))) -> Чемпионы
... A167: 4122 | B167: 45198 | C167: 31 | D167: 3196.4137 | E167: =DATE(2023,10,1)-B167 -> 2 | F167: =IF(E167<=30,5,IF(E167<=60,4,IF(E167<=90,3,IF(E167<=180,2,1)))) -> 5 | G167: =IF(C167>=25,5,IF(C167>=20,4,IF(C167>=15,3,IF(C167>=10,2,1)))) -> 5 | H167: =IF(D167>=2500,5,IF(D167>=2000,4,IF(D167>=1500,3,IF(D167>=1000,2,1)))) -> 5 | I167: =F167+G167+H167 -> 15 | J167: =IF(AND(F167>=4,G167>=4,H167>=4),"Чемпионы",IF(AND(F167>=3,G167>=4),"Лояльные",IF(AND(F167>=4,G167<=2),"Новые",IF(AND(F167<=2,G167>=4),"В зоне риска",IF(AND(F167<=2,G167<=2),"Потерянные","Прочие"))))) -> Чемпионы
A168: Общий итог | B168: 45200 | C168: 3357 | D168: 357025.63 | E168: =DATE(2023,10,1)-B168 -> 0 | F168: =IF(E168<=30,5,IF(E168<=60,4,IF(E168<=90,3,IF(E168<=180,2,1)))) -> 5 | G168: =IF(C168>=25,5,IF(C168>=20,4,IF(C168>=15,3,IF(C168>=10,2,1)))) -> 5 | H168: =IF(D168>=2500,5,IF(D168>=2000,4,IF(D168>=1500,3,IF(D168>=1000,2,1)))) -> 5 | I168: =F168+G168+H168 -> 15 | J168: =IF(AND(F168>=4,G168>=4,H168>=4),"Чемпионы",IF(AND(F168>=3,G168>=4),"Лояльные",IF(AND(F168>=4,G168<=2),"Новые",IF(AND(F168<=2,G168>=4),"В зоне риска",IF(AND(F168<=2,G168<=2),"Потерянные","Прочие"))))) -> Чемпионы

Sheet Сводная Парето
A3: Названия строк | B3: ID | C3: Сумма
A4: Да | B4: 119 | C4: 284880.25
A5: Нет | B5: 47 | C5: 72145.372
A6: Общий итог | B6: 166 | C6: 357025.63

Sheet Парето
A1: ID клиента | B1: Сумма покупок | C1: Накопленная сумма | D1: Накопленная доля | E1: Топ-80%
A2: 3957 | B2: 3690.6962 | C2: 3690.6962 | D2: =C2/SUM($B$2:$B$167) -> 0.010337342 | E2: =IF(D2<=0.8,"Да","Нет") -> Да
A3: 3958 | B3: 3625.0745 | C3: =C2+B3 -> 7315.7707 | D3: =C3/SUM($B$2:$B$167) -> 0.020490884 | E3: =IF(D3<=0.8,"Да","Нет") -> Да
A4: 3959 | B4: 3454.3156 | C4: =C3+B4 -> 10770.086 | D4: =C4/SUM($B$2:$B$167) -> 0.030166144 | E4: =IF(D4<=0.8,"Да","Нет") -> Да
A5: 3960 | B5: 3436.0648 | C5: =C4+B5 -> 14206.151 | D5: =C5/SUM($B$2:$B$167) -> 0.039790284 | E5: =IF(D5<=0.8,"Да","Нет") -> Да
A6: 3961 | B6: 3374.4755 | C6: =C5+B6 -> 17580.627 | D6: =C6/SUM($B$2:$B$167) -> 0.049241918 | E6: =IF(D6<=0.8,"Да","Нет") -> Да
A7: 3962 | B7: 3196.4137 | C7: =C6+B7 -> 20777.04 | D7: =C7/SUM($B$2:$B$167) -> 0.058194815 | E7: =IF(D7<=0.8,"Да","Нет") -> Да
A8: 3963 | B8: 3107.0669 | C8: =C7+B8 -> 23884.107 | D8: =C8/SUM($B$2:$B$167) -> 0.066897459 | E8: =IF(D8<=0.8,"Да","Нет") -> Да
A9: 3964 | B9: 3066.5074 | C9: =C8+B9 -> 26950.615 | D9: =C9/SUM($B$2:$B$167) -> 0.075486499 | E9: =IF(D9<=0.8,"Да","Нет") -> Да
A10: 3965 | B10: 2958.88 | C10: =C9+B10 -> 29909.495 | D10: =C10/SUM($B$2:$B$167) -> 0.083774083 | E10: =IF(D10<=0.8,"Да","Нет") -> Да
A11: 3966 | B11: 2905.6981 | C11: =C10+B11 -> 32815.193 | D11: =C11/SUM($B$2:$B$167) -> 0.091912709 | E11: =IF(D11<=0.8,"Да","Нет") -> Да
A12: 3967 | B12: 2864.1937 | C12: =C11+B12 -> 35679.386 | D12: =C12/SUM($B$2:$B$167) -> 0.099935085 | E12: =IF(D12<=0.8,"Да","Нет") -> Да
A13: 3968 | B13: 2855.1006 | C13: =C12+B13 -> 38534.487 | D13: =C13/SUM($B$2:$B$167) -> 0.10793199 | E13: =IF(D13<=0.8,"Да","Нет") -> Да
A14: 3969 | B14: 2848.3669 | C14: =C13+B14 -> 41382.854 | D14: =C14/SUM($B$2:$B$167) -> 0.11591004 | E14: =IF(D14<=0.8,"Да","Нет") -> Да
... A167: 4122 | B167: 1111.5921 | C167: =C166+B167 -> 357025.63 | D167: =C167/SUM($B$2:$B$167) -> 1 | E167: =IF(D167<=0.8,"Да","Нет") -> Нет
A168: Общий итог | B168: 357025.63
A169: Клиентов для 80% выручки: | B169: =COUNTIF(E2:E167,"Да") -> 119
A170: Доля от всех клиентов, % | B170: =B169/166 -> 0.71686747
A171: Выручка топ-80%, USD | B171: =SUMIF(E2:E167,"Да",B2:B167) -> 284880.25
A172: Общая выручка, USD | B172: =SUM(B2:B167) -> 357025.63
A173: Доля топ-80% в общей выручке, % | B173: =B171/B172 -> 0.79792663

Sheet Отчет
A1: АНАЛИЗ ПРОДАЖ FASHION RETAIL
A2: Отчёт подготовлен: Кудрявцевой Дианой
A3: Дата: 16.09.2026
A4: О данных
A5: Источник: Fashion_Retail_Sales.csv
A6: Период: 2022-10-02 — 2023-10-01
A7: Строк: 3357, клиентов: 166, товаров: 50
A8: Пропусков после очистки: 0
A11: Ключевые метрики
A12: Общая выручка, USD | B12: =Сводка!B5 -> 357025.63
A13: Средний чек, USD | B13: =Сводка!B6 -> 106.35258
A14: Медиана чека, USD | B14: =Сводка!B7 -> 107
A15: Средний рейтинг | B15: =Сводка!B14 -> 2.995061
A16: Уникальных клиентов | B16: =Сводка!B3 -> 166
A17: Уникальных товаров | B17: =Сводка!B4 -> 50
A18: Товары
A19: Топ-товар по выручке | B19: ='ABC-анализ'!A2 -> Skirt
A20: Выручка топ-товара, USD | B20: ='ABC-анализ'!E2 -> 9248.8
A21: Товаров класса A | B21: =COUNTIF('ABC-анализ'!H:H,"A") -> 21
A22: Товаров класса B | B22: =COUNTIF('ABC-анализ'!H:H,"B") -> 16
A23: Товаров класса C | B23: =COUNTIF('ABC-анализ'!H:H,"C") -> 13
A26: Клиенты
A27: Клиентов для 80% выручки | B27: =Парето!B169 -> 119
A28: Доля от всех клиентов, % | B28: =Парето!B170 -> 0.71686747
A29: Выручка топ-80%, USD | B29: =Парето!B171 -> 284880.25
A30: Доля топ-80% в выручке, % | B30: =Парето!B173 -> 0.79792663
A31: Кластеров (K-means) | B31: 4
A34: Ключевые выводы:
A35: 1. Общая выручка за год: 357 025 USD, средний чек 106 USD.
A36: 2. Товар влияет на чек и рейтинг (ANOVA, p < 0,001).
A37: 3. Способ оплаты не влияет на чек, рейтинг и выбор товара.
A38: 4. Пропуски в данных случайны (p = 0,87), заполнение не искажает картину.
A39: 5. 72% клиентов дают 80% выручки — база равномерная.
A40: 6. Корреляция суммы и рейтинга отсутствует (r = 0,03).
A41: 7. Прогноз выручки ненадёжен — R² < 0,05, тренда нет.
A43: Структура отчета
A44: • Данные — очищенные исходные данные
A45: • Сводка — описательная статистика
A46: • Товары, ABC-анализ — анализ ассортимента
... A53: • Дашборд — визуализации

Sheet Дашборд

Sheet Гипотезы
A1: Гипотеза | B1: Тест | C1: Статистика | D1: p-значение | E1: Результат
A2: H1: Средний чек отличается у Credit Card vs Cash | B2: Welch t-test | C2: -0.854 | D2: 0.3932 | E2: Не отвергаем H0
A3: H2: Средний рейтинг отличается у CC vs Cash | B3: Welch t-test | C3: 0.272 | D3: 0.7853 | E3: Не отвергаем H0
A4: H3: Средний чек отличается между товарами | B4: One-way ANOVA | C4: 2.076 | D4: 0.0 | E4: Отвергаем H0
A5: H4: Средний рейтинг отличается между товарами | B5: One-way ANOVA | C5: 2.062 | D5: 0.0 | E5: Отвергаем H0
A6: H5: Способ оплаты связан с товаром | B6: Chi-square | C6: 41.908 | D6: 0.7536 | E6: Не отвергаем H0
A7: H7: Средний рейтинг отличается по месяцам | B7: One-way ANOVA | C7: 1.512 | D7: 0.112 | E7: Не отвергаем H0
A8: H8: Средний чек отличается по дням недели | B8: One-way ANOVA | C8: 0.528 | D8: 0.7875 | E8: Не отвергаем H0

Sheet Корреляции
A1: Метрика | B1: Коэффициент | C1: p-значение | D1: Интерпретация
A2: Pearson: Сумма vs Рейтинг | B2: 0.0279 | C2: 0.1058 | D2: Связи нет
A3: Spearman: Сумма vs Рейтинг | B3: 0.0275 | C3: 0.1115 | D3: Связи нет
A4: Cramér's V: Оплата vs Товар | B4: 0.0 | D4: Независимы
A5: Point-biserial: Оплата vs Сумма | B5: -0.0147 | C5: 0.3935 | D5: Связи нет

Sheet Кластеры
A1: customer_id | B1: recency | C1: frequency | D1: monetary | E1: cluster | F1: cluster_name
A2: 3957 | B2: 86 | C2: 14 | D2: 1473.97 | E2: 2 | F2: Потерянные
A3: 3958 | B3: 18 | C3: 20 | D3: 1673.53 | E3: 0 | F3: Средние
A4: 3959 | B4: 29 | C4: 22 | D4: 2347.54 | E4: 1 | F4: Активные
A5: 3960 | B5: 18 | C5: 18 | D5: 1723.79 | E5: 0 | F5: Средние
A6: 3961 | B6: 34 | C6: 22 | D6: 2328.67 | E6: 1 | F6: Активные
A7: 3962 | B7: 7 | C7: 22 | D7: 2559.35 | E7: 1 | F7: Активные
A8: 3963 | B8: 5 | C8: 20 | D8: 2203.96 | E8: 1 | F8: Активные
A9: 3964 | B9: 8 | C9: 22 | D9: 2335.79 | E9: 1 | F9: Активные
A10: 3965 | B10: 4 | C10: 19 | D10: 2025.69 | E10: 1 | F10: Активные
A11: 3966 | B11: 15 | C11: 18 | D11: 2166.13 | E11: 1 | F11: Активные
A12: 3967 | B12: 6 | C12: 21 | D12: 2186.86 | E12: 1 | F12: Активные
A13: 3968 | B13: 11 | C13: 25 | D13: 2529.15 | E13: 1 | F13: Активные
... A167: 4122 | B167: 3 | C167: 31 | D167: 3196.41 | E167: 3 | F167: Активные

Sheet Прогноз
A1: month | B1: fact | C1: forecast
A2: 2022-10 | B2: 30615.08
A3: 2022-11 | B3: 25054.58
A4: 2022-12 | B4: 32170.75
A5: 2023-01 | B5: 30472.87
A6: 2023-02 | B6: 25843.94
A7: 2023-03 | B7: 30741.29
A8: 2023-04 | B8: 30732.61
A9: 2023-05 | B9: 31615.13
A10: 2023-06 | B10: 29972.7
A11: 2023-07 | B11: 31332.45
A12: 2023-08 | B12: 31507.79
A13: 2023-09 | B13: 26543.44
A14: 2023-10 | C14: 30222.04
A15: 2023-11 | C15: 30299.76
A16: 2023-12 | C16: 30377.47
